funmap/__init__.py
funmap/cli.py
funmap/data_urls.py
funmap/funmap.py
funmap/logger.py
funmap/plotting.py
funmap/saving.py
funmap/utils.py
funmap-0.2.2.dist-info/METADATA
funmap-0.2.2.dist-info/WHEEL
funmap-0.2.2.dist-info/entry_points.txt
funmap-0.2.2.dist-info/licenses/LICENSE
funmap-0.2.2.dist-info/RECORD
