Metadata-Version: 2.4
Name: funmap
Version: 0.2.2
Summary: generate gene co-function networks using omics data
Project-URL: Homepage, https://github.com/bzhanglab/funmap
Author-email: Zhiao Shi <zhiao.shi@gmail.com>
License: MIT license
License-File: LICENSE
Keywords: bioinformatics,biological-network,funmap
Requires-Python: >=3.8
Requires-Dist: click==8.1.7
Requires-Dist: h5py==3.10.0
Requires-Dist: imbalanced-learn==0.11.0
Requires-Dist: joblib==1.3.2
Requires-Dist: matplotlib-venn==0.11.9
Requires-Dist: matplotlib==3.7.3
Requires-Dist: networkx==3.1
Requires-Dist: numpy==1.24.4
Requires-Dist: pandas==2.0.3
Requires-Dist: powerlaw==1.5
Requires-Dist: pyarrow==13.0.0
Requires-Dist: pypdf2==3.0.1
Requires-Dist: pyyaml==6.0.1
Requires-Dist: scikit-learn==1.3.2
Requires-Dist: scipy==1.10.1
Requires-Dist: seaborn==0.13.0
Requires-Dist: tables>=3.8.0
Requires-Dist: tqdm==4.66.1
Requires-Dist: xgboost==2.0.0
Provides-Extra: testing
